passvalidate/__init__.py
passvalidate/password_checker.py
passvalidate-0.1.3.dist-info/LICENSE
passvalidate-0.1.3.dist-info/METADATA
passvalidate-0.1.3.dist-info/WHEEL
passvalidate-0.1.3.dist-info/RECORD
