Metadata-Version: 2.1
Name: passvalidate
Version: 0.1.3
Summary: A configurable password policy checker
Home-page: https://github.com/ygivenx/password-policy
Keywords: password,security,policy,check,auth,authentication
Author: Rohan Singh
Author-email: singhrohan@outlook.com
Requires-Python: >=3.8,<4.0
Classifier: Programming Language :: Python :: 3
Classifier: Programming Language :: Python :: 3.8
Classifier: Programming Language :: Python :: 3.9
Classifier: Programming Language :: Python :: 3.10
Classifier: Programming Language :: Python :: 3.11
Classifier: Programming Language :: Python :: 3.12
Project-URL: Repository, https://github.com/ygivenx/password-policy
